setuptools_vcs_version.py
setuptools_vcs_version-0.9.2.dist-info/METADATA
setuptools_vcs_version-0.9.2.dist-info/WHEEL
setuptools_vcs_version-0.9.2.dist-info/entry_points.txt
setuptools_vcs_version-0.9.2.dist-info/top_level.txt
setuptools_vcs_version-0.9.2.dist-info/RECORD
