Metadata-Version: 2.1
Name: setuptools-vcs-version
Version: 0.9.2
Summary: Automatically set package version from VCS.
Home-page: https://github.com/alesh/setuptools-vcs-version
Author: Alexey Poryadin
Author-email: alexey.poryadin@gmail.com
Maintainer: Alexey Poryadin, bobatsar
License: http://opensource.org/licenses/MIT
Keywords: setuptools git mercurial darcs subversion bazaar fossil version-control
Platform: UNKNOWN
Classifier: Framework :: Setuptools Plugin
Classifier: Intended Audience :: Developers
Classifier: License :: OSI Approved :: MIT License
Classifier: Programming Language :: Python
Requires-Dist: dunamai (>=1.1.0)
